arlas_subscriptions_manager_api_python/__init__.py
arlas_subscriptions_manager_api_python/api_client.py
arlas_subscriptions_manager_api_python/configuration.py
arlas_subscriptions_manager_api_python/rest.py
arlas_subscriptions_manager_api_python/api/__init__.py
arlas_subscriptions_manager_api_python/api/admin_api.py
arlas_subscriptions_manager_api_python/api/end_user_api.py
arlas_subscriptions_manager_api_python/models/__init__.py
arlas_subscriptions_manager_api_python/models/error.py
arlas_subscriptions_manager_api_python/models/hits.py
arlas_subscriptions_manager_api_python/models/link.py
arlas_subscriptions_manager_api_python/models/subscription.py
arlas_subscriptions_manager_api_python/models/subscription_list_resource.py
arlas_subscriptions_manager_api_python/models/user_subscription.py
arlas_subscriptions_manager_api_python/models/user_subscription_with_links.py
test/__init__.py
test/test_admin_api.py
test/test_end_user_api.py
test/test_error.py
test/test_hits.py
test/test_link.py
test/test_subscription.py
test/test_subscription_list_resource.py
test/test_user_subscription.py
test/test_user_subscription_with_links.py
arlas_subscriptions_manager_api-23.0.1.dist-info/METADATA
arlas_subscriptions_manager_api-23.0.1.dist-info/WHEEL
arlas_subscriptions_manager_api-23.0.1.dist-info/top_level.txt
arlas_subscriptions_manager_api-23.0.1.dist-info/RECORD
