Metadata-Version: 2.1
Name: arlas-subscriptions-manager-api
Version: 23.0.1
Summary: ARLAS Subscriptions Manager API
Home-page: https://github.com/gisaia/ARLAS-subscriptions
Author: Gisaïa
Author-email: contact@gisaia.com
License: UNKNOWN
Keywords: Arlas,ARLAS Subscriptions API
Platform: UNKNOWN
Requires-Dist: urllib3 (>=1.15)
Requires-Dist: six (>=1.10)
Requires-Dist: certifi
Requires-Dist: python-dateutil
